bbc/__init__.py
bbc/anthologies/download_acl.sh
bbc/anthologies/download_jmlr.sh
bbc/anthologies/download_nips.sh
bbc/anthologies/download_pmlr.sh
bbc/anthologies/validate.py
bbc/bbc.py
bbc-0.1.1.dist-info/entry_points.txt
bbc-0.1.1.dist-info/LICENSE
bbc-0.1.1.dist-info/WHEEL
bbc-0.1.1.dist-info/METADATA
bbc-0.1.1.dist-info/RECORD
